{
    "Application Information": [
        "CheckPermission",
        "GetAppName",
        "GetAppPath",
        "GetBuildNum",
        "GetDSVersion",
        "GetName",
        "GetOptions",
        "GetPackageName",
        "GetPermission",
        "GetVersion",
        "InIDE",
        "IsAPK",
        "IsAppInstalled",
        "IsDebugEnabled",
        "IsDebugging",
        "IsEngine",
        "IsNewVersion",
        "IsPremium",
        "IsService",
        "IsStarted",
        "IsThings"
    ],
    "Application Control": [
        "CreateDebug",
        "Debug",
        "Error",
        "Execute",
        "Exit",
        "ExtExec",
        "GetNotifyId",
        "GetObjects",
        "GoToSleep",
        "KillApp",
        "LoadPlugin",
        "LoadScript",
        "Script",
        "SetAlarm",
        "SetAutoStart",
        "SetAutoWifi",
        "SetDebug",
        "SetDebugEnabled",
        "SetInBackground",
        "SetInForeground",
        "SetKioskMode",
        "SetLanguage",
        "SetOnDebug",
        "SetOnError",
        "SetOptions",
        "SetPriority",
        "SetTitle",
        "ShowDebug",
        "Start",
        "StartApp",
        "StopApp",
        "ToBack",
        "ToFront",
        "Unlock",
        "Wait",
        "WakeUp"
    ],
    "Bluetooth": [
        "CreateBluetoothList",
        "CreateBluetoothSerial",
        "DiscoverBtDevices",
        "GetBluetoothAddress",
        "GetBluetoothName",
        "GetBtProfileState",
        "GetPairedBtDevices",
        "IsBluetoothEnabled",
        "IsBluetoothOn",
        "IsBtDevicePaired",
        "PairBtDevice",
        "SetBluetoothEnabled",
        "UnpairBtDevice"
    ],
    "Components": [
        "CreateCrypt",
        "CreateLocator",
        "CreateMediaStore",
        "CreatePhoneState",
        "CreatePlayStore",
        "CreateService",
        "CreateSpeechRec",
        "CreateSysProc",
        "CreateUSBSerial",
        "CreateWebServer",
        "StartService",
        "StopService"
    ],
    "Controls": [
        "CreateButton",
        "CreateCameraView",
        "CreateCheckBox",
        "CreateCodeEdit",
        "CreateGLView",
        "CreateImage",
        "CreateList",
        "CreateListDialog",
        "CreateListView",
        "CreateScroller",
        "CreateSeekBar",
        "CreateSpinner",
        "CreateTabs",
        "CreateText",
        "CreateTextEdit",
        "CreateTheme",
        "CreateToggle",
        "CreateVideoView",
        "CreateWebView"
    ],
    "Cross-Application": [
        "Broadcast",
        "BroadcastIntent",
        "GetIntent",
        "GetSharedFiles",
        "GetSharedText",
        "SendIntent",
        "SendText",
        "SetOnBroadcast",
        "SetSharedApp"
    ],
    "Database": [
        "ClearData",
        "ClearValue",
        "DeleteDatabase",
        "GetData",
        "GetDatabaseFolder",
        "LoadBoolean",
        "LoadNumber",
        "LoadText",
        "OpenDatabase",
        "QueryContent",
        "SaveBoolean",
        "SaveCookies",
        "SaveNumber",
        "SaveText",
        "SetData"
    ],
    "Device Information": [
        "GetActivities",
        "GetBatteryLevel",
        "GetChargeType",
        "GetDefaultOrientation",
        "GetDeviceId",
        "GetEnv",
        "GetInstalledApps",
        "GetKeyboardHeight",
        "GetMemoryInfo",
        "GetModel",
        "GetOSVersion",
        "GetRunningApps",
        "GetRunningServices",
        "HasSoftNav",
        "IsCharging",
        "IsChrome",
        "IsKeyboardShown",
        "IsLocationEnabled",
        "IsNavBarOnRight",
        "IsScreenOn",
        "IsTablet",
        "IsWifiApEnabled"
    ],
    "Device Control": [
        "CreateNotification",
        "CreateNxt",
        "CreateNxtRemote",
        "CreateSensor",
        "CreateShortcut",
        "CreateSmartWatch",
        "DisableTouch",
        "EnableBackKey",
        "GetClipboardText",
        "GetJoystickName",
        "GetJoystickState",
        "GetVolume",
        "InstallWallpaper",
        "Lock",
        "Odroid",
        "PlaySound",
        "PreventScreenLock",
        "Quit",
        "ScreenShot",
        "SetAutoBoot",
        "SetClipboardText",
        "SetDensity",
        "SetJoystickOptions",
        "SetOnKey",
        "SetOnShowKeyboard",
        "SetScreenBrightness",
        "SetScreenMode",
        "SetVolume",
        "SetWifiApEnabled",
        "ShowKeyboard",
        "ShowMenu",
        "SysExec",
        "Vibrate",
        "DisableKeys",
        "WifiScan"
    ],
    "Dialogs": [
        "Alert",
        "CreateDialog",
        "CreateNotification",
        "CreateYesNoDialog",
        "HideProgress",
        "HideProgressBar",
        "ShowPopup",
        "ShowProgress",
        "ShowProgressBar",
        "ShowTextDialog",
        "ShowTip",
        "UpdateProgressBar"
    ],
    "Files": [
        "ChooseFile",
        "ChooseImage",
        "CopyFile",
        "CopyFolder",
        "CreateFile",
        "CreateZipUtil",
        "DeleteFile",
        "DeleteFolder",
        "ExtractAssets",
        "ExtractPlugins",
        "FileExists",
        "FolderExists",
        "GetExternalFolder",
        "GetFileDate",
        "GetFileSize",
        "GetFreeSpace",
        "GetInternalFolder",
        "GetMediaFile",
        "GetMetadata",
        "GetPath",
        "GetPrivateFolder",
        "GetResourceId",
        "GetSpecialFolder",
        "GetThumbnail",
        "IsFolder",
        "ListFolder",
        "MakeFolder",
        "OpenFile",
        "ReadFile",
        "RenameFile",
        "RenameFolder",
        "ReplaceInFile",
        "ScanFile",
        "SendFile",
        "UnzipFile",
        "Uri2Path",
        "WriteFile",
        "ZipFile",
        "ZipFolder"
    ],
    "Graphics": [
        "Animate",
        "CreateGLView",
        "CreateGame",
        "CreateGameView",
        "CreateImage",
        "GetDisplayHeight",
        "GetDisplayWidth",
        "GetOrientation",
        "GetRotation",
        "GetScreenDensity",
        "GetScreenHeight",
        "GetScreenWidth",
        "SetOrientation"
    ],
    "Layouts": [
        "AddDrawer",
        "AddLayout",
        "CloseDrawer",
        "CreateLayout",
        "CreateOverlay",
        "CreateWallpaper",
        "CreateWizard",
        "DestroyDrawer",
        "DestroyLayout",
        "GetDrawerState",
        "InstallWallpaper",
        "LockDrawer",
        "OpenDrawer",
        "RemoveDrawer",
        "UnlockDrawer"
    ],
    "Messaging": [
        "Call",
        "CreateEmail",
        "CreateSMS",
        "SendMail",
        "SendMessage",
        "SendSMS"
    ],
    "Network": [
        "ChooseWifi",
        "ClearCookies",
        "CreateEmail",
        "CreateNetClient",
        "CreateWebSocket",
        "CreateWebView",
        "DownloadFile",
        "GetIPAddress",
        "GetMacAddress",
        "GetRSSI",
        "CreateDownloader",
        "GetSSID",
        "HttpRequest",
        "IsConnected",
        "IsWifiEnabled",
        "OpenUrl",
        "PreventWifiSleep",
        "SetOnWifiChange",
        "SetUserAgent",
        "SetUserCreds",
        "SetWifiEnabled",
        "StartDebugServer",
        "StopDebugServer",
        "UploadFile",
        "WifiConnect"
    ],
    "Obj": [
        "AdjustColor",
        "ClearFocus",
        "Destroy",
        "Focus",
        "GetAbsHeight",
        "GetAbsWidth",
        "GetHeight",
        "GetLeft",
        "GetPosition",
        "GetTop",
        "GetVisibility",
        "GetWidth",
        "Gone",
        "Hide",
        "IsEnabled",
        "IsVisible",
        "Release",
        "SetBackAlpha",
        "SetBackColor",
        "SetBackGradient",
        "SetBackGradientRadial",
        "SetBackground",
        "SetColorFilter",
        "SetEnabled",
        "SetMargins",
        "SetPadding",
        "SetPosition",
        "SetScale",
        "SetSize",
        "SetVisibility",
        "Show",
        "Tween",
        "_left",
        "_top",
        "id"
    ],
    "Sounds": [
        "CreateAudioRecorder",
        "CreateMediaPlayer",
        "CreateSynth",
        "GetRingerMode",
        "GetSpeakerPhone",
        "GetVolume",
        "PlayRingtone",
        "SetRingerMode",
        "SetSpeakerPhone",
        "SetVolume",
        "TextToSpeech",
        "Vibrate"
    ],
    "SObj": [
        "Destroy",
        "Release",
        "id"
    ],
    "UI Control": [
        "GetLastButton",
        "GetLastCheckBox",
        "GetLastImage",
        "GetLastToggle",
        "GetObjects",
        "HideKeyboard",
        "RemoveLayout",
        "SetKioskMode",
        "SetMenu",
        "SetTheme",
        "SimulateDrag",
        "SimulateKey",
        "SimulateScroll",
        "SimulateTouch"
    ],
    "User Information": [
        "CheckLicense",
        "ChooseAccount",
        "ChooseContact",
        "GetAccounts",
        "GetCountry",
        "GetCountryCode",
        "GetLanguage",
        "GetLanguageCode",
        "GetUser",
        "Language2Code"
    ]
}
